yaml_wrapper/__init__.py
yaml_wrapper/API/__init__.py
yaml_wrapper/API/yaml_wrapper.py
yaml_wrapper/modules/__init__.py
yaml_wrapper/modules/converters/__init__.py
yaml_wrapper/modules/converters/to_json_converter.py
yaml_wrapper/modules/initialisers/__init__.py
yaml_wrapper/modules/initialisers/initialiser.py
yaml_wrapper/modules/modification_handlers/__init__.py
yaml_wrapper/modules/modification_handlers/modification_handler.py
yaml_wrapper/modules/modification_handlers/exceptions/__init__.py
yaml_wrapper/modules/modification_handlers/exceptions/filter_not_found_exception.py
yaml_wrapper/modules/modification_handlers/exceptions/key_already_used_exception.py
yaml_wrapper/modules/modification_handlers/exceptions/not_safe_load_exception.py
yaml_wrapper/modules/modification_handlers/exceptions/not_valid_filter_exception.py
yaml_wrapper/modules/modification_handlers/exceptions/not_valid_remove_exception.py
yaml_wrapper/modules/modification_handlers/exceptions/not_valid_update_exception.py
yaml_wrapper/modules/modification_handlers/utils/__init__.py
yaml_wrapper/modules/modification_handlers/utils/searchers/__init__.py
yaml_wrapper/modules/modification_handlers/utils/searchers/object_by_path_reference_searcer.py
yaml_wrapper/modules/modification_handlers/utils/searchers/value_by_path_boolean_searcher.py
yaml_wrapper/modules/modification_handlers/utils/searchers/value_by_path_reference_searcher.py
yaml_wrapper/modules/synchronisers/__init__.py
yaml_wrapper/modules/synchronisers/synchroniser.py
yaml_wrapper/modules/synchronisers/exceptions/__init__.py
yaml_wrapper/modules/synchronisers/exceptions/not_synchronisable_object_exception.py
yaml_wrapper/modules/translators/__init__.py
yaml_wrapper/modules/translators/from_yaml_traslator.py
yaml_wrapper/modules/translators/to_yaml_translator.py
yaml_wrapper/modules/translators/enums/__init__.py
yaml_wrapper/modules/translators/enums/object_type.py
yaml_wrapper/modules/translators/enums/rule_type.py
PythonYamlWrapper-1.2.2.dist-info/LICENSE
PythonYamlWrapper-1.2.2.dist-info/METADATA
PythonYamlWrapper-1.2.2.dist-info/WHEEL
PythonYamlWrapper-1.2.2.dist-info/top_level.txt
PythonYamlWrapper-1.2.2.dist-info/RECORD
