Metadata-Version: 2.1
Name: PythonYamlWrapper
Version: 1.2.2
Summary: YamlWrapper is a wrapper for yaml files, that creates an abstraction layer in order to handle yaml files in a easy way.
Author-email: Alexandru Dumitru <aaaalexdumitru@gmail.com>
License: MIT License
Project-URL: Documentation, https://alexandruparaschivdumitru.github.io/yaml_wrapper/src/API/yaml_wrapper.html
Project-URL: Source, https://github.com/alexandruparaschivdumitru/yaml_wrapper
Project-URL: Bug Tracker, https://github.com/alexandruparaschivdumitru/yaml_wrapper/issues
Classifier: Programming Language :: Python :: 3
Classifier: License :: OSI Approved :: MIT License
Requires-Python: >=3.8
License-File: LICENSE
Requires-Dist: PyYAML
